spacy_ngram/__init__.py
spacy_ngram/ngram_component.py
spacy_ngram-0.0.3.dist-info/LICENSE
spacy_ngram-0.0.3.dist-info/WHEEL
spacy_ngram-0.0.3.dist-info/METADATA
spacy_ngram-0.0.3.dist-info/RECORD
