Metadata-Version: 2.1
Name: spacy-ngram
Version: 0.0.3
Summary: SpaCy pipeline component for adding document or sentence-level ngrams.
Keywords: nlp,ngrams
Author-email: dcronkite <dcronkite+pypi@gmail.com>
Requires-Python: >=3.10
Classifier: Development Status :: 4 - Beta
Classifier: Intended Audience :: Science/Research
Classifier: Programming Language :: Python :: 3 :: Only
Classifier: Topic :: Text Processing :: Linguistic
Classifier: License :: OSI Approved :: MIT License
Requires-Dist: spacy
Requires-Dist: pytest ; extra == "dev"
Project-URL: Home, https://github.com/kpwhri/spacy-ngram
Provides-Extra: dev
